pyros/__init__.py
pyros/__main__.py
pyros/_version.py
pyros/config.py
pyros/client/__init__.py
pyros/client/client.py
pyros/server/__init__.py
pyros/server/ctx_server.py
pyros-0.4.3.dist-info/METADATA
pyros-0.4.3.dist-info/RECORD
pyros-0.4.3.dist-info/WHEEL
pyros-0.4.3.dist-info/dependency_links.txt
pyros-0.4.3.dist-info/entry_points.txt
pyros-0.4.3.dist-info/pbr.json
pyros-0.4.3.dist-info/top_level.txt
